[
{"url":"http://i.imgur.com/yZfPbr6.jpg"},  
{"url":"http://i.imgur.com/ITI3A3z.gif"},  
{"url":"http://i.imgur.com/88gjY.gif"},  
{"url":"http://i.imgur.com/B6WlRrt.gif"},  
{"url":"http://i.imgur.com/zrO55cS.jpg"},  
{"url":"https://i.imgur.com/K8SgyLO.png"},  
{"url":"http://i.imgur.com/4y197.gif"},  
{"url":"https://i.imgur.com/9ZmzmVx.gif"},  
{"url":"https://i.imgur.com/tUNgsjk.jpg"},  
{"url":"http://i.imgur.com/21BNobv.jpg"},  
{"url":"http://i.imgur.com/BGWQvMA.gif"},  
{"url":"http://i.imgur.com/Ic1P4i3.png"},  
{"url":"https://i.imgur.com/yWaQYWn.jpg"},  
{"url":"http://imgur.com/BX9Cu.jpg"},  
{"url":"http://i.imgur.com/S8EP8FU.gif"},  
{"url":"http://i.imgur.com/qX6eGag.gif"},  
{"url":"http://i.imgur.com/EeZ9CfE.gif"},  
{"url":"http://i.imgur.com/wH7unDI.jpg"},  
{"url":"http://i.imgur.com/ilKDIPh.jpg"},  
{"url":"http://i.imgur.com/Zf9rszd.gif"},  
{"url":"https://i.imgur.com/RwGbcon.gif"},  
{"url":"http://i.imgur.com/o04L8oX.jpg"},  
{"url":"http://i.imgur.com/sMDsm8M.gif"},  
{"url":"http://i.imgur.com/9I1j171.jpg"},  
{"url":"http://i.imgur.com/kL5yTOk.jpg"},  
{"url":"http://i.imgur.com/dSjVVXk.jpg"},  
{"url":"http://i.imgur.com/AnTnSA9.jpg"},  
{"url":"http://i.imgur.com/dfuNDxO.jpg"},  
{"url":"http://i.imgur.com/ai3mR.jpg"},  
{"url":"http://i.imgur.com/Y68KW.jpg"},  
{"url":"http://i.imgur.com/rL6YaJE.jpg"},  
{"url":"http://i.imgur.com/RYOtp6j.jpg"},  
{"url":"http://i.imgur.com/ebHgJsc.gif"},  
{"url":"http://i.imgur.com/Tk4PEdM.jpg"},  
{"url":"http://i.imgur.com/RCvclC5.gif"},  
{"url":"http://i.minus.com/i5sOhWIZ1nqtT.gif"},  
{"url":"https://i.imgur.com/5ci8m9N.gif"},  
{"url":"http://24.media.tumblr.com/ca73cc0998e10675d0a92e71a9660d64/tumblr_mo8j02p3Ji1ryino5o1_500.gif"},  
{"url":"https://i.imgur.com/mJwpSJa.png"},  
{"url":"http://i.imgur.com/UFRXXR0.gif"},  
{"url":"https://i.imgur.com/jb1DctO.gif"},  
{"url":"http://i.imgur.com/PVyq73f.jpg"},  
{"url":"https://i.imgur.com/oq8cnti.gif"},  
{"url":"https://i.imgur.com/qKmTKc9.png"},  
{"url":"http://i.imgur.com/HdoLtS4.jpg"},  
{"url":"http://i.imgur.com/b9Cpurs.jpg"},  
{"url":"http://i.imgur.com/UJ0xM9X.jpg"},  
{"url":"http://i.imgur.com/0Ld3w.jpg"},  
{"url":"http://i.imgur.com/E26cKvK.gif"},  
{"url":"http://i.imgur.com/Zx0LwJE.jpg"},  
{"url":"http://i.imgur.com/EZa18Qf.gif"},  
{"url":"https://i.imgur.com/pCgfvlX.png"},  
{"url":"https://i.imgur.com/azcZona.gif"},  
{"url":"http://i.imgur.com/UZDgFqX.jpg"},  
{"url":"http://i.imgur.com/kkXWtLR.jpg"},  
{"url":"http://i.imgur.com/1D2vq.gif"},  
{"url":"https://i.imgur.com/I9ZSxvg.jpg"},  
{"url":"http://24.media.tumblr.com/be01b5ad81947cfb2757f817b2534fbc/tumblr_n0d16bixoj1ts03z2o1_500.gif"},  
{"url":"https://i.imgur.com/6cvT6hY.gif"},  
{"url":"https://i.imgur.com/7HAL1K6.gif"},  
{"url":"http://i.imgur.com/JlF1pb9.jpg"},  
{"url":"https://i.imgur.com/ZwVA2yp.gif"},  
{"url":"http://i.imgur.com/1FCvw.jpg"},  
{"url":"http://i.imgur.com/YBRp6.jpg"},  
{"url":"http://i.imgur.com/KQ96NGi.jpg"},  
{"url":"https://i.imgur.com/OLgw3CT.gif"},  
{"url":"https://i.imgur.com/fREP3Mv.png"},  
{"url":"https://i.imgur.com/fwqtJoH.gif"},  
{"url":"http://i.imgur.com/LxtwMsq.gif"},  
{"url":"https://i.imgur.com/Efij1Hs.gif"},  
{"url":"http://i.imgur.com/nrzWepd.jpg"},  
{"url":"http://i.imgur.com/DTGkZWX.gif"},  
{"url":"http://i.imgur.com/HOuAJpu.jpg"},  
{"url":"http://i.imgur.com/TIpl0.jpg"},  
{"url":"http://i.imgur.com/Y5COg.jpg"},  
{"url":"http://i.imgur.com/OYCri.jpg"},  
{"url":"http://i.imgur.com/0sPcy.jpg"},  
{"url":"http://i.imgur.com/FVOZqAT.jpg"},  
{"url":"http://i.imgur.com/F8llq.jpg"},  
{"url":"https://i.imgur.com/vDZpHd4.png"},  
{"url":"https://i.imgur.com/zWYvmsr.png"},  
{"url":"https://i.imgur.com/5DBVN0x.gif"},  
{"url":"http://i.imgur.com/YW4jg5i.jpg"},  
{"url":"https://i.imgur.com/LYAT8w8.png"},  
{"url":"https://i.imgur.com/z0Pvu3V.gif"},  
{"url":"http://i.imgur.com/xY9y1aP.gif"},  
{"url":"https://i.imgur.com/bAdMmkK.png"},  
{"url":"https://i.imgur.com/z1GttH7.gif"},  
{"url":"http://i.imgur.com/FPRMJyz.gif"},  
{"url":"http://i.imgur.com/ZLhYe30.jpg"},  
{"url":"http://i.imgur.com/BE1F3uP.gif"},  
{"url":"http://i.imgur.com/GbB5Nfd.gif"},  
{"url":"http://i.imgur.com/jRqFN.jpg"},  
{"url":"https://i.imgur.com/kkvxyUR.png"},  
{"url":"http://i.imgur.com/K4kRkl2.jpg"},  
{"url":"http://i.imgur.com/eA3H6DL.gif"},  
{"url":"http://i.imgur.com/a8RqV5k.jpg"},  
{"url":"https://i.imgur.com/FG9G90Y.png"},  
{"url":"https://i.imgur.com/8zF8jO3.gif"},  
{"url":"https://i.imgur.com/qclpQa9.gif"},  
{"url":"http://i.imgur.com/kJ5o58f.gif"},  
{"url":"http://i.imgur.com/WeuSJzb.jpg"},  
{"url":"http://i.imgur.com/h001w.gif"},  
{"url":"https://i.imgur.com/2eH2w3j.png"},  
{"url":"http://i.imgur.com/WEm3khQ.gif"},  
{"url":"http://i.imgur.com/iffrEl3.gif"},  
{"url":"https://i.imgur.com/FGFbtaj.jpg"},  
{"url":"https://i.imgur.com/5alrWay.jpg"},  
{"url":"http://i.imgur.com/BcrRc2j.jpg"},  
{"url":"http://i.imgur.com/OOXAvSn.jpg"},  
{"url":"https://i.imgur.com/aLtSm4J.png"},  
{"url":"https://i.imgur.com/ENejuFg.gif"},  
{"url":"https://i.imgur.com/Ij0AG9M.jpg"},  
{"url":"http://i.imgur.com/bRi4Lq8.gif"},  
{"url":"http://i.minus.com/ibl8fQsMxyM8ux.gif"},  
{"url":"https://i.imgur.com/hgs1OlU.png"},  
{"url":"http://i.imgur.com/5UDdLxe.jpg"},  
{"url":"http://i.imgur.com/h4OMKc1.gif"},  
{"url":"https://i.imgur.com/MqUCkn6.gif"},  
{"url":"http://i.imgur.com/c7yjQ.jpg"},  
{"url":"http://i.imgur.com/IdOByCj.jpg"},  
{"url":"https://i.imgur.com/J24N2T6.jpg"},  
{"url":"http://i.imgur.com/LhVb8sy.jpg"},  
{"url":"https://i.imgur.com/rwWiB17.jpg"}, 
{"url":"https://i.imgur.com/jIOVX0P.gif"},  
{"url":"https://i.imgur.com/Yia4DxB.png"},  
{"url":"https://i.imgur.com/3mgAtO4.png"},  
{"url":"http://i.imgur.com/4NsjNoE.jpg"},  
{"url":"http://i.imgur.com/yP8asJZ.jpg"},  
{"url":"http://i.imgur.com/Nn5cG6j.gif"},  
{"url":"http://i.imgur.com/9tWaqqa.jpg"},  
{"url":"https://i.imgur.com/G04MAdW.png"},  
{"url":"https://i.imgur.com/0H3VcS4.gif"},  
{"url":"https://i.imgur.com/RJGDTNt.jpg"},  
{"url":"http://25.media.tumblr.com/4cca2269c323fac855bbee1440c77483/tumblr_mlz0642pOQ1spwt1fo1_500.gif"},  
{"url":"http://i.imgur.com/8qGKPMS.jpg"},  
{"url":"http://i.minus.com/iZonNBqZzErnq.gif"},  
{"url":"https://i.imgur.com/ntggtix.gif"},  
{"url":"https://i.imgur.com/G1xjPv6.gif"},  
{"url":"https://i.imgur.com/LhVb8sy.png"},  
{"url":"https://i.imgur.com/3YcviRa.gif"},  
{"url":"http://i.imgur.com/cKWD05F.gif"},  
{"url":"http://i.imgur.com/youciK5.gif"},  
{"url":"http://24.media.tumblr.com/7a66a6c0cbee073b6d17482c05fc124d/tumblr_mno4thEupn1ryino5o8_400.gif"},  
{"url":"https://i.imgur.com/WhVT80F.gif"},  
{"url":"https://i.imgur.com/kXV8B72.png"},  
{"url":"https://i.imgur.com/h0aiYyR.gif"},  
{"url":"https://i.imgur.com/jFzFDFh.png"},  
{"url":"http://i.imgur.com/3EgqMyU.jpg"},  
{"url":"http://i.imgur.com/7M2QrqG.jpg"},  
{"url":"http://i.imgur.com/e9ljDP8.jpg"},  
{"url":"https://i.imgur.com/ks86IOJ.jpg"},  
{"url":"http://i.imgur.com/hCsDVV5.jpg"},  
{"url":"http://i.imgur.com/6t9jnBz.jpg"},  
{"url":"http://i.imgur.com/OSc0L.jpg"},  
{"url":"https://i.imgur.com/sErItN6.jpg"},  
{"url":"http://i.imgur.com/ChtcPtB.gif"},  
{"url":"http://i.imgur.com/zFaJ60Z.jpg"},  
{"url":"http://i.imgur.com/H2hTS6U.gif"},  
{"url":"http://i.imgur.com/tr0eNSh.jpg"},  
{"url":"http://i.imgur.com/jRMoqwf.jpg"},  
{"url":"http://i.imgur.com/g6IvuCG.jpg"},  
{"url":"http://i.imgur.com/t9CldXq.jpg"},  
{"url":"http://i.imgur.com/Coa70PF.jpg"},  
{"url":"http://i.imgur.com/0bVTDHK.jpg"},  
{"url":"http://i.imgur.com/g46iN2B.jpg"},  
{"url":"http://i.imgur.com/yoAwf58.jpg"},  
{"url":"http://i.imgur.com/9UfS3ku.jpg"},  
{"url":"https://i.imgur.com/ZEjO2nf.png"},  
{"url":"https://i.imgur.com/r1XRFLc.png"},  
{"url":"https://i.imgur.com/AJlXkAL.jpg"},  
{"url":"http://i.imgur.com/ORHfKAO.jpg"},  
{"url":"http://i.imgur.com/jIcho.gif"},  
{"url":"https://i.imgur.com/lVc4pQl.png"},  
{"url":"http://i.imgur.com/rzuhg.jpg"},  
{"url":"https://i.imgur.com/tXiF3M9.png"},  
{"url":"https://i.imgur.com/pmKH9uf.png"},  
{"url":"http://i.imgur.com/mJwpSJa.jpg"},  
{"url":"http://i.imgur.com/HV6On6e.jpg"},  
{"url":"http://24.media.tumblr.com/9696cd6c48df4d267787c705c590dde4/tumblr_mmr9wemmkM1ryino5o3_500.gif"},  
{"url":"http://i.imgur.com/uXHOyIY.jpg"},  
{"url":"https://i.imgur.com/ytoYS4E.png"},  
{"url":"http://i.imgur.com/M292i.gif"},  
{"url":"https://i.imgur.com/1p0dbb1.png"},  
{"url":"https://i.imgur.com/wqC57Yz.gif"},  
{"url":"https://i.imgur.com/ULh11Jy.gif"},  
{"url":"https://i.imgur.com/71H4v2p.mp4"},  
{"url":"http://i.imgur.com/bESF7KS.mp4"},  
{"url":"http://i.imgur.com/ooXQveP.jpg"},  
{"url":"http://i.imgur.com/CrAeYFj.gif"},  
{"url":"http://i.imgur.com/BZHzWAW.jpg"},  
{"url":"https://i.imgur.com/iLALTaa.gif"},  
{"url":"https://i.imgur.com/7ZR27D6.png"},  
{"url":"https://i.imgur.com/pf6U4eT.png"},  
{"url":"http://i.imgur.com/ADmTH8e.jpg"},  
{"url":"http://i.imgur.com/VbX9P.jpg"},  
{"url":"https://i.imgur.com/ioiuw0c.gif"},  
{"url":"https://i.imgur.com/27IcvvH.gif"},  
{"url":"https://i.imgur.com/zna0tMB.png"},  
{"url":"https://i.imgur.com/d0FBUOm.png"},  
{"url":"https://i.imgur.com/zdZBzod.png"},  
{"url":"https://i.imgur.com/LTJkqnt.png"},  
{"url":"http://i.imgur.com/jYRSz2m.jpg"},  
{"url":"http://i.imgur.com/54Ku2tR.gif"},  
{"url":"http://i.imgur.com/VHRcVlv.jpg"},  
{"url":"https://i.imgur.com/xxL4L8S.jpg"},  
{"url":"https://i.imgur.com/GJjh2bX.jpg"},  
{"url":"https://i.imgur.com/u8GW7Zx.gif"},  
{"url":"https://i.imgur.com/KCTMvSx.gif"},  
{"url":"http://i.imgur.com/UvlYsNb.jpg"},  
{"url":"http://i.imgur.com/GjOOQ2Q.jpg"},  
{"url":"https://i.imgur.com/33WCisc.png"},  
{"url":"http://i.imgur.com/c9ShYfM.jpg"},  
{"url":"http://i.imgur.com/3Zt8PJt.jpg"},  
{"url":"https://i.imgur.com/3OOFXoZ.png"},  
{"url":"https://i.imgur.com/NHWCCLs.png"},  
{"url":"https://i.imgur.com/8BXaN1T.png"},  
{"url":"https://i.imgur.com/0ajgbIX.gif"},  
{"url":"https://i.imgur.com/GYeKpLq.gif"},  
{"url":"http://i.imgur.com/IhsCQ3w.jpg"},  
{"url":"http://i.imgur.com/6Z6YGGN.jpg"},  
{"url":"http://i.imgur.com/0zDkKYT.gif"},  
{"url":"http://i.imgur.com/DHu2Vzh.gif"},  
{"url":"http://i.imgur.com/AdcmN.jpg"},  
{"url":"https://i.imgur.com/RseOxNK.png"},  
{"url":"https://i.imgur.com/uYAZ3kd.gif"},  
{"url":"https://i.imgur.com/uPFXNGM.gif"},  
{"url":"https://i.imgur.com/FkVk2B2.jpg"},  
{"url":"https://i.imgur.com/taTxncp.jpg"},  
{"url":"http://i.imgur.com/3nTgs7d.gif"},  
{"url":"http://i.imgur.com/vWmQjt8.jpg"},  
{"url":"http://i.imgur.com/kRm1pVq.jpg"},  
{"url":"http://i.imgur.com/tsac6v0.jpg"},  
{"url":"http://i.imgur.com/Zn3wZ2f.jpg"},  
{"url":"http://i.imgur.com/cIaArAx.jpg"},  
{"url":"http://i.imgur.com/O0rhMFM.jpg"},  
{"url":"https://i.imgur.com/e2KOwID.jpg"},  
{"url":"http://i.imgur.com/eRYNOEg.jpg"},  
{"url":"http://i.imgur.com/RQe5FWe.jpg"},  
{"url":"https://i.imgur.com/l4sLAxp.gif"},  
{"url":"https://i.imgur.com/TwUKlGv.png"},  
{"url":"https://i.imgur.com/sx89XtR.png"},  
{"url":"https://i.imgur.com/hnVkDzm.png"},  
{"url":"https://i.imgur.com/EZFEdTV.png"},  
{"url":"http://i.imgur.com/BcBGM2P.jpg"},  
{"url":"http://i.imgur.com/33WCisc.jpg"},  
{"url":"http://i.imgur.com/vPgFyCo.jpg"},  
{"url":"http://i.imgur.com/os2R1TX.gif"},  
{"url":"http://i.imgur.com/Ir8r0zo.jpg"},  
{"url":"http://i.imgur.com/IaCA0lZ.gif"},  
{"url":"http://i.imgur.com/XMl8o.gif"},  
{"url":"https://i.imgur.com/Vtrs4GW.png"},  
{"url":"https://i.imgur.com/WGoSdXH.png"},  
{"url":"https://i.imgur.com/W2OZWva.png"},  
{"url":"http://i.imgur.com/DezpWI0.png"},  
{"url":"http://i.imgur.com/gieC1Og.png"},  
{"url":"http://i.imgur.com/OnzXCmb.jpg"},  
{"url":"http://i.imgur.com/coxdoFt.gif"},  
{"url":"https://i.imgur.com/935jT7h.jpg"},  
{"url":"http://i.imgur.com/jFtAn7B.gif"},  
{"url":"http://i.imgur.com/ZmRtT4z.jpg"},  
{"url":"http://i.imgur.com/L4wb7Sj.jpg"},  
{"url":"http://i.imgur.com/gKWM51S.jpg"},  
{"url":"http://i.imgur.com/iOQmyJG.jpg"},  
{"url":"http://i.imgur.com/7devegH.jpg"},  
{"url":"http://i.imgur.com/ntYhi2C.jpg"},  
{"url":"http://i.imgur.com/o0xoTCR.jpg"},  
{"url":"https://i.imgur.com/TS8WRos.gif"},  
{"url":"https://i.imgur.com/KBgbr1Y.png"},  
{"url":"https://i.imgur.com/LLhKCKD.png"},  
{"url":"http://i.imgur.com/XDh1dAT.jpg"},  
{"url":"http://i.imgur.com/eiW8HNz.gif"},  
{"url":"http://i.imgur.com/y6cYVd5.jpg"},  
{"url":"http://i.imgur.com/jGt5DZd.jpg"},  
{"url":"http://i.imgur.com/K0srCiV.jpg"},  
{"url":"http://i.imgur.com/9nVgoCE.jpg"},  
{"url":"http://i.imgur.com/f1sykI4.jpg"},  
{"url":"https://i.imgur.com/n9zoyVq.png"},  
{"url":"https://i.imgur.com/W6dJmr5.png"},  
{"url":"https://i.imgur.com/P7WIPVl.png"},  
{"url":"http://i.imgur.com/eAgZpxg.gif"},  
{"url":"http://i.imgur.com/6tM3btk.gif"},  
{"url":"http://i.imgur.com/Fj5zL.jpg"},  
{"url":"http://i.imgur.com/TbbDQJc.gif"},  
{"url":"https://i.imgur.com/it4P9ZL.gif"},  
{"url":"http://i.imgur.com/fJKgn9M.jpg"},  
{"url":"http://i.imgur.com/NXxal5M.jpg"},  
{"url":"http://i.imgur.com/n4DtdpL.gif"},  
{"url":"http://i.imgur.com/I8dV9HB.gif"},  
{"url":"http://i.minus.com/iblVC2uV8hUPKb.gif"},  
{"url":"https://i.imgur.com/v28tpp7.gif"},  
{"url":"https://i.imgur.com/aW9lgJS.png"},  
{"url":"https://i.imgur.com/PkmJbAv.gif"},  
{"url":"https://i.imgur.com/ukcL2DA.png"},  
{"url":"https://i.imgur.com/iLXk2on.jpg"},  
{"url":"https://i.imgur.com/wILdjbz.jpg"},  
{"url":"http://i.imgur.com/ur9KW8y.gif"},  
{"url":"http://i.imgur.com/FuoKF83.jpg"},  
{"url":"http://i.imgur.com/GmmcWsl.jpg"},  
{"url":"http://i.imgur.com/85hJaNB.jpg"},  
{"url":"https://i.imgur.com/L8eIw1B.gif"},  
{"url":"https://i.imgur.com/wcxxHP9.gif"},  
{"url":"https://i.imgur.com/0DoW6NTh.jpg"},  
{"url":"https://i.imgur.com/vE5LiWq.png"},  
{"url":"http://i.imgur.com/YawU6II.jpg"},  
{"url":"http://i.imgur.com/2v1EcKN.gif"},  
{"url":"http://i.imgur.com/JS59dDp.jpg"},  
{"url":"http://i.imgur.com/ZVhZYn7.png"},  
{"url":"http://i.imgur.com/pezfNAf.gif"},  
{"url":"http://i.imgur.com/x9lYyhr.gif"},  
{"url":"http://i.imgur.com/iuOud.jpg"},  
{"url":"https://i.imgur.com/9WTqUeM.gif"},  
{"url":"https://i.imgur.com/E8XOtaN.png"},  
{"url":"http://i.imgur.com/pxlm8n4.jpg"},  
{"url":"http://i.imgur.com/jZIHXiz.jpg"},  
{"url":"https://i.imgur.com/f1COnYj.png"},  
{"url":"https://i.imgur.com/rUaYI9A.jpg"},  
{"url":"http://i.imgur.com/76Qz2U7.jpg"},  
{"url":"http://i.imgur.com/z9MesX2.jpg"},  
{"url":"http://i.imgur.com/EPJFcMj.jpg"},  
{"url":"http://i.imgur.com/K6RzNpR.gif"},  
{"url":"http://i.imgur.com/SreQ5lB.mp4"},  
{"url":"http://i.imgur.com/r6UlM8g.gif"},  
{"url":"http://i.imgur.com/eifzMwv.jpg"},  
{"url":"http://i.imgur.com/qyHot3n.gif"},  
{"url":"https://i.imgur.com/khLxi4b.gif"},  
{"url":"https://i.imgur.com/tq9IPjd.png"},  
{"url":"http://i.imgur.com/XgFnBCr.gif"},  
{"url":"http://i.imgur.com/fg1hcxy.gif"},  
{"url":"http://i.imgur.com/OIpHagP.gif"},  
{"url":"http://i.imgur.com/P3pwgZX.jpg"},  
{"url":"https://i.imgur.com/fbB5lgU.jpg"},  
{"url":"http://i.imgur.com/tBMFMJJ.jpg"},  
{"url":"http://i.imgur.com/1L3an0B.gif"},  
{"url":"http://i.imgur.com/k5PGKRX.gif"},  
{"url":"https://i.imgur.com/uPmHFBl.jpg"},  
{"url":"http://i.imgur.com/fO9B5.gif"},  
{"url":"http://i.imgur.com/T1kAe.gif"},  
{"url":"https://i.imgur.com/mIkF8Je.gif"},  
{"url":"https://i.imgur.com/NvBFj4v.gif"},  
{"url":"https://i.imgur.com/waRNQhS.gif"},  
{"url":"https://i.imgur.com/3E0VNAa.gif"},  
{"url":"https://i.imgur.com/fpMtnvq.png"},  
{"url":"https://i.imgur.com/ipvLtt3.jpg"},  
{"url":"http://i.imgur.com/gDnskON.jpg"},  
{"url":"http://i.imgur.com/YAdIaNy.gif"},  
{"url":"http://i.imgur.com/a0XMMSU.gif"},  
{"url":"http://i.imgur.com/JjvPCFF.gif"},  
{"url":"http://i.imgur.com/2YKDTyu.jpg"},  
{"url":"http://i.imgur.com/C7htn.gif"},  
{"url":"https://i.imgur.com/EtFQblC.png"},  
{"url":"https://i.imgur.com/Q1TeJuv.png"},  
{"url":"https://i.imgur.com/SABPk97.jpg"},  
{"url":"http://i.imgur.com/LLhKCKD.jpg"},  
{"url":"http://i.imgur.com/NKIagbb.jpg"},  
{"url":"http://i.imgur.com/ObaT0Z2.gif"},  
{"url":"http://i.imgur.com/8RGeO9g.jpg"},  
{"url":"http://i.imgur.com/8TxTq.jpg"},  
{"url":"https://i.imgur.com/fiAbgif.png"},  
{"url":"https://i.imgur.com/XjKd4BC.png"},  
{"url":"https://i.imgur.com/GLXe1Ji.png"},  
{"url":"https://i.imgur.com/LijGy0Q.png"},  
{"url":"https://i.imgur.com/Xbyv4dv.png"},  
{"url":"https://i.imgur.com/khUYLD1.jpg"},  
{"url":"http://i.imgur.com/ITa4OX3.gif"},  
{"url":"http://i.imgur.com/CuYTFV6.jpg"},  
{"url":"http://i.imgur.com/xuuHOie.gif"},  
{"url":"http://i.imgur.com/QpwhseN.gif"},  
{"url":"http://i.imgur.com/5ivSFXz.gif"},  
{"url":"http://i.imgur.com/7Ii02ek.jpg"},  
{"url":"http://i.imgur.com/b4nh6.jpg"},  
{"url":"https://i.imgur.com/81aXTAL.png"},  
{"url":"https://i.imgur.com/w7IgIUG.png"},  
{"url":"https://i.imgur.com/Pb1FZJ9.png"},  
{"url":"https://i.imgur.com/Z7oqRT3.gif"},  
{"url":"https://i.imgur.com/XJ7xZ4n.png"},  
{"url":"https://i.imgur.com/htHMfgj.png"},  
{"url":"http://i.imgur.com/KJUt5mI.jpg"},  
{"url":"http://i.imgur.com/kkvxyUR.jpg"},  
{"url":"http://i.imgur.com/ey0owVe.jpg"},  
{"url":"http://i.imgur.com/aLyfEwt.jpg"},  
{"url":"http://i.imgur.com/JTuH2f5.jpg"},  
{"url":"http://i.imgur.com/O7HXWKA.jpg"},  
{"url":"http://i.imgur.com/756ZYqg.gif"},  
{"url":"http://i.imgur.com/PgpPBn3.gif"},  
{"url":"http://i.imgur.com/5HZX2.jpg"},  
{"url":"https://i.imgur.com/2mXE4vy.gif"},  
{"url":"https://i.imgur.com/EEvjuhL.gif"},  
{"url":"https://i.imgur.com/PZUvg7U.png"},  
{"url":"https://i.imgur.com/Mwymig0.png"},  
{"url":"https://i.imgur.com/8UVvneM.png"},  
{"url":"https://i.imgur.com/kWjPmya.gif"},  
{"url":"https://i.imgur.com/vnI9EsF.jpg"},  
{"url":"http://i.imgur.com/Dc3aMdK.gif"},  
{"url":"http://i.imgur.com/dnliW7N.gif"},  
{"url":"http://i.imgur.com/MrpFaTG.gif"},  
{"url":"http://i.imgur.com/U5gPJ.jpg"},  
{"url":"https://i.imgur.com/PPiu7KE.gif"},  
{"url":"https://i.imgur.com/pzlbk6d.png"},  
{"url":"https://i.imgur.com/Ys3KTUH.jpg"},  
{"url":"https://i.imgur.com/8xjdN01.jpg"},  
{"url":"http://i.imgur.com/dwFANVV.jpg"},  
{"url":"http://i.imgur.com/e6Sd2ed.jpg"},  
{"url":"http://i.imgur.com/wyh0ioX.jpg"},  
{"url":"http://i.imgur.com/3GoM3Th.jpg"},  
{"url":"http://i.imgur.com/2G3r0Dl.jpg"},  
{"url":"http://i.imgur.com/73oDw.gif"},  
{"url":"https://i.imgur.com/JbU3gTI.png"},  
{"url":"https://i.imgur.com/QQeKv5x.png"},  
{"url":"https://i.imgur.com/3Zt8PJt.png"},  
{"url":"https://i.imgur.com/kIyMmdJ.gif"},  
{"url":"https://i.imgur.com/UxiJU9J.gif"},  
{"url":"https://i.imgur.com/4QNxs45.png"},  
{"url":"https://i.imgur.com/UGIHuTl.gif"},  
{"url":"https://i.imgur.com/apzLnIj.gif"},  
{"url":"http://i.imgur.com/hCVILCQ.jpg"},  
{"url":"http://i.imgur.com/J9BekY0.jpg"},  
{"url":"http://i.imgur.com/PlvH9.jpg"},  
{"url":"http://i.imgur.com/IWBCm.jpg"},  
{"url":"http://i.imgur.com/OaUmb.gif"},  
{"url":"https://i.imgur.com/ZRiyP2r.png"},  
{"url":"https://i.imgur.com/18Rlzdt.png"},  
{"url":"https://i.imgur.com/B9PnX5A.png"},  
{"url":"https://i.imgur.com/L0uFONt.png"},  
{"url":"https://i.imgur.com/UvlYsNb.png"},  
{"url":"https://i.imgur.com/FpI9NpZ.jpg"},  
{"url":"http://i.imgur.com/XL50Fcu.jpg"},  
{"url":"http://i.imgur.com/pCgfvlX.jpg"},  
{"url":"http://i.imgur.com/29iaVt7.gif"},  
{"url":"http://i.imgur.com/USNK2mP.gif"},  
{"url":"http://i.imgur.com/AoKZ9L5.jpg"},  
{"url":"http://i.imgur.com/9lZ1LTA.gif"},  
{"url":"http://i.imgur.com/9pJec5V.gif"},  
{"url":"http://i.imgur.com/faLPNZ9.gif"},  
{"url":"http://i.imgur.com/1h0bnHS.jpg"},  
{"url":"http://i.imgur.com/wBOU2US.jpg"},  
{"url":"http://i.imgur.com/kRDNo.jpg"},  
{"url":"http://i.imgur.com/11dvtSD.jpg"},  
{"url":"https://i.imgur.com/7oWdG9U.png"},  
{"url":"https://i.imgur.com/aqICOoD.png"},  
{"url":"https://i.imgur.com/LfdNFWo.gif"},  
{"url":"https://i.imgur.com/qzfbXoP.gif"},  
{"url":"https://i.imgur.com/J9BekY0.png"},  
{"url":"http://i.imgur.com/EbDrQ3V.jpg"},  
{"url":"http://i.imgur.com/n0rJ1ok.jpg"},  
{"url":"http://i.imgur.com/V4sQZk6.jpg"},  
{"url":"http://i.imgur.com/MMrjMIe.gif"},  
{"url":"http://i.imgur.com/VBJyIOQ.jpg"},  
{"url":"http://i.imgur.com/YYQLzXy.jpg"},  
{"url":"https://i.imgur.com/dEShBcG.gif"},  
{"url":"https://i.imgur.com/lwdWFO5.mp4"},  
{"url":"https://i.imgur.com/eMupcxz.png"},  
{"url":"http://i.imgur.com/lvtGy3S.mp4"},  
{"url":"http://i.imgur.com/76xwiYJ.jpg"},  
{"url":"https://i.imgur.com/ZQRmRNz.jpg"},  
{"url":"http://i.imgur.com/2HXXbWV.gif"},  
{"url":"http://i.imgur.com/jIbTjbb.jpg"},  
{"url":"http://i.imgur.com/CtHRKll.gif"},  
{"url":"http://i.imgur.com/coIBFJE.gif"},  
{"url":"http://i.imgur.com/m6OAMe1.jpg"},  
{"url":"http://i.imgur.com/3ygtZ.jpg"},  
{"url":"https://i.imgur.com/HQzVVw7.gif"},  
{"url":"https://i.imgur.com/qwGATLb.gif"},  
{"url":"https://i.imgur.com/S8IHnDE.png"},  
{"url":"https://i.imgur.com/7neeuxp.gif"},  
{"url":"https://i.imgur.com/KWSlJoh.jpg"},  
{"url":"https://i.imgur.com/7YTyAnw.png"},  
{"url":"https://i.imgur.com/XY1DOAM.mp4"},  
{"url":"http://i.imgur.com/TUZfOfe.gif"},  
{"url":"http://i.imgur.com/BxJPi8x.jpg"},  
{"url":"http://i.imgur.com/H0B7unX.gif"},  
{"url":"https://i.imgur.com/Da8UAZ8h.jpg"},  
{"url":"http://i.imgur.com/cvK8qGd.gif"},  
{"url":"http://i.imgur.com/JrHVIiY.gif"},  
{"url":"http://i.imgur.com/FsPJ5N3.jpg"},  
{"url":"http://i.imgur.com/3PF77LV.gif"},  
{"url":"https://i.imgur.com/FfNl8XL.jpg"},  
{"url":"http://i.imgur.com/m1opn35.jpg"},  
{"url":"http://i.imgur.com/N4qrR.jpg"},  
{"url":"http://i.imgur.com/vfs92.gif"},  
{"url":"https://i.imgur.com/VijjcpM.png"},  
{"url":"https://i.imgur.com/9Fi71zy.png"},  
{"url":"https://i.imgur.com/aNWTdTS.png"},  
{"url":"https://i.imgur.com/kLML8Q9.gif"},  
{"url":"https://i.imgur.com/M3rbReH.png"},  
{"url":"https://i.imgur.com/0SVnMe9.png"},  
{"url":"https://i.imgur.com/HCCnrGi.gif"},  
{"url":"https://i.imgur.com/sYe7U6p.png"},  
{"url":"http://i.imgur.com/wDzhhFM.jpg"},  
{"url":"http://i.imgur.com/Uc8D4vI.mp4"},  
{"url":"http://i.imgur.com/Vru4isv.jpg"},  
{"url":"http://i.imgur.com/oNHpCYD.gif"},  
{"url":"http://i.imgur.com/Q7emw3c.gif"},  
{"url":"http://i.imgur.com/rwX2bJu.gif"},  
{"url":"https://i.imgur.com/0CPRSl7.jpg"},  
{"url":"http://i.imgur.com/IrWw8lA.mp4"},  
{"url":"https://i.imgur.com/zTMji70.png"},  
{"url":"http://i.imgur.com/qXBLffT.jpg"},  
{"url":"https://i.imgur.com/yIlPpbw.png"},  
{"url":"https://i.imgur.com/U9kPp9W.mp4"},  
{"url":"https://i.imgur.com/2C35J.mp4"},  
{"url":"https://i.imgur.com/Fuh3WI0.jpg"},  
{"url":"http://i.imgur.com/0sbqwSO.jpg"},  
{"url":"http://i.imgur.com/WXmlzdp.gif"},  
{"url":"http://i.imgur.com/VJMKGwB.gif"},  
{"url":"http://i.imgur.com/OsjBBcJ.jpg"},  
{"url":"http://i.imgur.com/1Rc7qa8.gif"},  
{"url":"http://i.imgur.com/EXhumYO.gif"},  
{"url":"http://i.imgur.com/kGq1UEj.gif"},  
{"url":"http://25.media.tumblr.com/tumblr_mbdvyxQPb81rf3sf4o1_400.gif"},  
{"url":"https://i.imgur.com/yzcue59.gif"},  
{"url":"https://i.imgur.com/P98qw5e.png"},  
{"url":"https://i.imgur.com/cfEvn4E.gif"},  
{"url":"https://i.imgur.com/K4kRkl2.png"},  
{"url":"https://i.imgur.com/szIMCNI.mp4"},  
{"url":"https://i.imgur.com/pnX2Y8d.png"},  
{"url":"https://i.imgur.com/7wnb2Sq.png"},  
{"url":"https://i.imgur.com/6W1LhNy.gif"},  
{"url":"http://i.imgur.com/Ah2uqv1.png"},  
{"url":"http://i.imgur.com/moMYV9M.mp4"},  
{"url":"http://i.imgur.com/WhVT80F.mp4"},  
{"url":"http://i.imgur.com/3DuG2Df.jpg"},  
{"url":"http://i.imgur.com/h3Dj0cF.jpg"},  
{"url":"http://i.imgur.com/pzO4gjS.gif"},  
{"url":"http://i.imgur.com/w9BGYJd.jpg"},  
{"url":"http://i.imgur.com/LeW2jWe.mp4"},  
{"url":"http://i.imgur.com/4rxYDBp.mp4"},  
{"url":"https://i.imgur.com/NN2cS1m.jpg"},  
{"url":"http://i.imgur.com/18OS3aV.jpg"},  
{"url":"http://i.imgur.com/uQUevOt.gif"},  
{"url":"http://i.imgur.com/gYX3KQU.gif"},  
{"url":"http://i.imgur.com/YCuL8Cl.jpg"},  
{"url":"http://i.imgur.com/xVhn6E9.gif"},  
{"url":"https://i.imgur.com/Kl6JYpc.jpg"},  
{"url":"http://i.imgur.com/4Kax6Il.jpg"},  
{"url":"https://i.imgur.com/VWRS9qQh.jpg"},  
{"url":"http://i.imgur.com/RSrpq.jpg"},  
{"url":"http://i.imgur.com/LQOWt.gif"},  
{"url":"https://i.imgur.com/pO7Plj0.png"},  
{"url":"https://i.imgur.com/0CHvE8f.png"},  
{"url":"https://i.imgur.com/7m2pTEV.png"},  
{"url":"https://i.imgur.com/HWWvFcc.png"},  
{"url":"https://i.imgur.com/UHvnAUl.png"},  
{"url":"https://i.imgur.com/tDhBrxx.png"},  
{"url":"http://i.imgur.com/B745i8c.jpg"},  
{"url":"http://i.imgur.com/gztFvZ3.mp4"},  
{"url":"http://i.imgur.com/VO0f9RE.jpg"},  
{"url":"http://i.imgur.com/7OLINNn.gif"},  
{"url":"http://i.imgur.com/nuJRd27.gif"},  
{"url":"http://i.imgur.com/AroWTe2.gif"},  
{"url":"http://i.imgur.com/YoTQttw.gif"},  
{"url":"http://i.imgur.com/nNCqPuf.jpg"},  
{"url":"http://i.imgur.com/9a0vCBw.jpg"},  
{"url":"http://i.imgur.com/m77pI.jpg"},  
{"url":"https://i.imgur.com/n0rJ1ok.png"},  
{"url":"https://i.imgur.com/nWA7Ga0.gif"},  
{"url":"https://i.imgur.com/ZxnnEDA.png"},  
{"url":"https://i.imgur.com/LOb9Nqgh.jpg"},  
{"url":"https://i.imgur.com/rQaszvS.jpg"},  
{"url":"https://i.imgur.com/Y27l0TC.mp4"},  
{"url":"https://i.imgur.com/rCcFins.png"},  
{"url":"http://i.imgur.com/x9PFHR6.jpg"},  
{"url":"http://i.imgur.com/vedC4OS.jpg"},  
{"url":"http://i.imgur.com/apyDarn.jpg"},  
{"url":"http://i.imgur.com/lceNXPz.jpg"},  
{"url":"http://i.imgur.com/mxHqn1y.jpg"},  
{"url":"http://i.imgur.com/fREP3Mv.jpg"},  
{"url":"http://i.imgur.com/wcZknGO.jpg"},  
{"url":"http://i.imgur.com/wqLCCFQ.jpg"},  
{"url":"https://i.imgur.com/s26cObe.jpg"},  
{"url":"http://i.imgur.com/iuMLM0x.gif"},  
{"url":"https://i.imgur.com/2GTXd0T.jpg"},  
{"url":"http://i.imgur.com/Vi0099T.jpg"},  
{"url":"http://i.minus.com/ibhG3MYFtWpFqk.gif"},  
{"url":"http://i.imgur.com/y5IiZ.gif"},  
{"url":"https://i.imgur.com/aeWyx9T.gif"},  
{"url":"http://i.imgur.com/yq2E57p.jpg"},  
{"url":"https://i.imgur.com/FDwExug.png"},  
{"url":"https://i.imgur.com/K6RzNpR.mp4"},  
{"url":"https://i.imgur.com/pFDkSb1.gif"},  
{"url":"https://i.imgur.com/zU8iADI.gif"},  
{"url":"https://i.imgur.com/AvstkJ4.gif"},  
{"url":"http://i.imgur.com/kMTxwXt.mp4"}, 
{"url":"http://i.imgur.com/7asdhU7.jpg"}, 
{"url":"http://i.imgur.com/iRdKCbQ.jpg"},  
{"url":"http://i.imgur.com/ah4DJwi.gif"},  
{"url":"http://i.imgur.com/5ZEzV7w.jpg"},  
{"url":"http://i.imgur.com/ALbIVWs.jpg"},  
{"url":"http://i.imgur.com/ygPIifW.jpg"},  
{"url":"http://i.imgur.com/somomTS.gif"},  
{"url":"http://i.imgur.com/v4nnagC.gif"},  
{"url":"http://i.imgur.com/THNTX5s.jpg"},  
{"url":"http://i.imgur.com/hfVUq26.gif"},  
{"url":"http://i.imgur.com/yqy7ibX.jpg"},  
{"url":"http://i.imgur.com/L2WRR61.gif"},  
{"url":"http://i.imgur.com/dtkKy64.jpg"},  
{"url":"https://i.imgur.com/2wlBWJH.jpg"}, 
{"url":"https://i.imgur.com/RQqJCCL.png"},  
{"url":"https://i.imgur.com/4TQNKli.gif"},  
{"url":"https://i.imgur.com/HxA8kTC.png"},  
{"url":"https://i.imgur.com/FqOvJfJ.gif"},  
{"url":"https://i.imgur.com/go8v3Mu.gif"},  
{"url":"https://i.imgur.com/h7H7ayC.png"},  
{"url":"https://i.imgur.com/6OLxfju.gif"},  
{"url":"https://i.imgur.com/ytnddUB.mp4"},  
{"url":"http://i.imgur.com/mgJ0mU9.mp4"},  
{"url":"http://i.imgur.com/jIPILeB.jpg"},  
{"url":"http://i.imgur.com/a4780M8.gif"},  
{"url":"http://i.imgur.com/u1ZdCzW.mp4"},  
{"url":"http://i.imgur.com/ThUI0aa.gif"},  
{"url":"http://i.imgur.com/iQUCs.jpg"},  
{"url":"http://i.imgur.com/Z4qqq.jpg"},  
{"url":"http://i.imgur.com/1Ewgt.jpg"},  
{"url":"http://i.imgur.com/H46B4.jpg"},  
{"url":"http://i.imgur.com/TW4Wl.jpg"},  
{"url":"http://i.imgur.com/jfUjY.jpg"},  
{"url":"http://i.imgur.com/AU7uq.jpg"},  
{"url":"http://i.imgur.com/5qFig.jpg"},  
{"url":"http://i.imgur.com/JN4bQ.jpg"},  
{"url":"http://i.imgur.com/ydswU.jpg"},  
{"url":"http://i.imgur.com/7a1aL.jpg"},  
{"url":"http://i.imgur.com/7wUMY.jpg"},  
{"url":"http://i.imgur.com/4oN0I.jpg"},  
{"url":"http://i.imgur.com/OjVam.jpg"},  
{"url":"http://i.imgur.com/4mYQG.jpg"},  
{"url":"https://i.redd.it/9c7bog6lama21.gif"},  
{"url":"https://i.imgur.com/dW7Rr55.gif"},  
{"url":"https://i.imgur.com/Qh4Lqn1.gif"},  
{"url":"https://i.imgur.com/6sAexES.mp4"},  
{"url":"https://i.imgur.com/vscDwGy.png"},  
{"url":"https://i.imgur.com/qjXKFEb.mp4"},  
{"url":"http://i.imgur.com/emoDUvA.mp4"},  
{"url":"http://i.imgur.com/oHghXZe.mp4"},  
{"url":"http://i.imgur.com/c0He8fr.jpg"},  
{"url":"https://i.imgur.com/PCV1uMTh.jpg"},  
{"url":"http://i.imgur.com/Ufzmo3U.gif"},  
{"url":"http://i.imgur.com/xKalifl.gif"},  
{"url":"http://i.imgur.com/XeMLw2e.jpg"},  
{"url":"http://i.imgur.com/GHhNeVM.gif"},  
{"url":"http://i.imgur.com/CfUTShO.jpg"},  
{"url":"http://i.imgur.com/wM6nE53.gif"},  
{"url":"http://i.imgur.com/qCmOKzO.jpg"},  
{"url":"http://i.imgur.com/dzzguTV.mp4"},  
{"url":"http://i.imgur.com/ov3dslX.gif"},  
{"url":"http://i.imgur.com/GE3ds.jpg"},  
{"url":"http://i.imgur.com/taUec.gif"},  
{"url":"http://i.imgur.com/qsmtaaI.jpg"},  
{"url":"https://i.imgur.com/xVJSaLY.png"},  
{"url":"https://i.imgur.com/4rmqoW6.png"},  
{"url":"https://i.imgur.com/lEsn0eC.gif"},  
{"url":"https://i.imgur.com/UKZlxze.gif"},  
{"url":"https://i.imgur.com/9TDXaBQ.png"},  
{"url":"https://i.imgur.com/vFBsnAE.mp4"},  
{"url":"http://i.imgur.com/kmnYgVa.jpg"},  
{"url":"http://i.imgur.com/nWA7Ga0.mp4"},  
{"url":"http://i.imgur.com/dq2dC82.jpg"},  
{"url":"http://i.imgur.com/FTuAAEN.jpg"},  
{"url":"http://i.imgur.com/0x9hwgf.mp4"},  
{"url":"http://i.imgur.com/J0289.jpg"},  
{"url":"http://i.imgur.com/uWmNBuz.gif"},  
{"url":"http://i.imgur.com/jEuTS.jpg"},  
{"url":"https://i.imgur.com/yY5dKgn.png"},  
{"url":"https://i.imgur.com/0xweuN3.gif"},  
{"url":"https://i.imgur.com/28W5XxNh.jpg"},  
{"url":"https://i.imgur.com/YawU6II.png"},  
{"url":"https://i.imgur.com/of7dBov.mp4"},  
{"url":"https://i.imgur.com/cqQOxTq.png"},  
{"url":"https://i.imgur.com/MbX0rS3.png"},  
{"url":"https://i.imgur.com/ATMzf7O.mp4"},  
{"url":"http://i.imgur.com/wqLCCFQ.png"},  
{"url":"http://i.imgur.com/7UgM3dR.jpg"},  
{"url":"http://i.imgur.com/4QZkLbb.jpg"},  
{"url":"http://i.imgur.com/Z6hFOUF.jpg"},  
{"url":"http://i.imgur.com/KuyMGJO.jpg"},  
{"url":"http://i.imgur.com/8qK0QP5.jpg"},  
{"url":"http://i.imgur.com/AgTkkV8.jpg"},  
{"url":"http://i.imgur.com/nc6nviV.jpg"},  
{"url":"http://i.imgur.com/6wMFbeN.jpg"},  
{"url":"http://i.imgur.com/9CyHOnB.jpg"},  
{"url":"http://i.imgur.com/lNv73Fu.jpg"},  
{"url":"http://i.imgur.com/CwLFF9a.jpg"},  
{"url":"http://i.imgur.com/9guSECk.jpg"},  
{"url":"http://i.imgur.com/4EKgnZi.jpg"},  
{"url":"http://i.imgur.com/7WSIXdN.jpg"},  
{"url":"http://i.imgur.com/dediAFO.jpg"},  
{"url":"http://i.imgur.com/IUZEuJp.jpg"},  
{"url":"http://i.imgur.com/WZAz9eL.jpg"},  
{"url":"http://i.imgur.com/Swgxg11.jpg"},  
{"url":"http://i.imgur.com/dtTkcQM.jpg"},  
{"url":"http://i.imgur.com/tDr8tz5.jpg"},  
{"url":"http://i.imgur.com/Stdv9V9.jpg"},  
{"url":"http://i.imgur.com/8SodLaM.jpg"},  
{"url":"http://i.imgur.com/7HM7N3k.jpg"},  
{"url":"http://i.imgur.com/ZOIzLYr.jpg"},  
{"url":"http://i.imgur.com/9QmRbtf.jpg"},  
{"url":"http://i.imgur.com/vjDaRik.jpg"},  
{"url":"http://i.imgur.com/Cy3b9Iq.jpg"},  
{"url":"http://i.imgur.com/JPpYBPz.jpg"},  
{"url":"http://i.imgur.com/9CpInzh.jpg"},  
{"url":"http://i.imgur.com/l7iX9D7.jpg"},  
{"url":"http://i.imgur.com/k2eoffi.jpg"},  
{"url":"http://i.imgur.com/i36D79w.jpg"},  
{"url":"http://i.imgur.com/2e3zXxT.jpg"},  
{"url":"http://i.imgur.com/Xwz10XP.jpg"},  
{"url":"http://i.imgur.com/q4xbExD.jpg"},  
{"url":"http://i.imgur.com/uCYJyF0.jpg"},  
{"url":"http://i.imgur.com/bmkxr5J.jpg"},  
{"url":"http://i.imgur.com/WSH359j.jpg"},  
{"url":"http://i.imgur.com/Iydxzic.jpg"},  
{"url":"http://i.imgur.com/TlAh9qT.jpg"},  
{"url":"http://i.imgur.com/mnzq920.jpg"},  
{"url":"http://i.imgur.com/E7dR2D5.jpg"},  
{"url":"http://i.imgur.com/by9Beqh.jpg"},  
{"url":"http://i.imgur.com/89oQyTP.jpg"},  
{"url":"http://i.imgur.com/wRCU6xp.jpg"},  
{"url":"http://i.imgur.com/LfVx1iR.jpg"},  
{"url":"http://i.imgur.com/aV74jbO.jpg"},  
{"url":"http://i.imgur.com/yIxhYUS.jpg"},  
{"url":"http://i.imgur.com/y4bYSpV.jpg"},  
{"url":"http://i.imgur.com/bICbFeL.jpg"},  
{"url":"http://i.imgur.com/gBsXH41.jpg"},  
{"url":"http://i.imgur.com/5vROsxK.jpg"},  
{"url":"http://i.imgur.com/xC7cc4Z.mp4"},  
{"url":"http://i.imgur.com/wyLGiXW.jpg"},  
{"url":"http://i.imgur.com/ldMjbHa.gif"},  
{"url":"http://i.imgur.com/LwXQ4mH.jpg"},  
{"url":"http://i.imgur.com/ytoYS4E.jpg"},  
{"url":"http://i.imgur.com/pPKjixz.jpg"},  
{"url":"http://i.imgur.com/RNUDBSt.jpg"},  
{"url":"http://i.imgur.com/TNd71O6.mp4"},  
{"url":"http://i.imgur.com/KxfscgA.jpg"},  
{"url":"http://i.imgur.com/HShQYcb.gif"},  
{"url":"https://i.imgur.com/ULMrMiB.png"},  
{"url":"https://i.imgur.com/R66ve8U.png"},  
{"url":"https://i.imgur.com/6UPtG3U.png"},  
{"url":"https://i.imgur.com/5ZEzV7w.png"},  
{"url":"https://i.imgur.com/BmPmVoQ.mp4"},  
{"url":"https://i.imgur.com/dM3AIIw.mp4"},  
{"url":"https://i.imgur.com/afLfIzB.png"},  
{"url":"https://i.imgur.com/PnIOA6c.png"},  
{"url":"https://i.imgur.com/FXVFBxU.png"},  
{"url":"http://i.imgur.com/c7ZQrf8.jpg"},  
{"url":"http://i.imgur.com/EA5HZdi.jpg"},  
{"url":"http://i.imgur.com/eGvfcPR.jpg"},  
{"url":"http://i.imgur.com/fGSrEuy.jpg"},  
{"url":"http://i.imgur.com/0YUxJvH.jpg"},  
{"url":"http://i.imgur.com/SXbpzUe.gif"},  
{"url":"http://i.imgur.com/xrtT6GO.gif"},  
{"url":"http://i.imgur.com/TzgIbki.mp4"},  
{"url":"http://i.imgur.com/sEOpRTJ.jpg"},  
{"url":"http://i.imgur.com/yWRSOUG.gif"},  
{"url":"https://i.imgur.com/CxA7nn7.gif"},  
{"url":"https://i.imgur.com/skIaffo.png"},  
{"url":"https://i.imgur.com/EbDW0za.png"},  
{"url":"https://i.imgur.com/x2mO8Vq.gif"},  
{"url":"https://i.imgur.com/Laoi7FN.gif"},  
{"url":"https://i.imgur.com/eGv3X9I.gif"},  
{"url":"https://i.imgur.com/DYDpYyU.gif"},  
{"url":"https://i.imgur.com/LJC6Sf4.mp4"},  
{"url":"https://i.imgur.com/Y2kIhOW.png"},  
{"url":"https://i.imgur.com/VvER9Ph.gif"},  
{"url":"https://i.imgur.com/aSmYHon.png"},  
{"url":"http://i.imgur.com/JKhbAZU.mp4"},  
{"url":"http://i.imgur.com/o0iWoep.gif"},  
{"url":"http://i.imgur.com/ypaI5o3.mp4"},  
{"url":"http://i.imgur.com/Mnu76UI.gif"},  
{"url":"http://i.imgur.com/TIBmn96.gif"},  
{"url":"http://i.imgur.com/ggViklx.gif"},  
{"url":"http://i.imgur.com/u6CdjYw.gif"},  
{"url":"http://i.imgur.com/SvHat.jpg"},  
{"url":"http://i.imgur.com/4X5X4.gif"},  
{"url":"https://i.imgur.com/YWR9ccq.gif"},  
{"url":"https://i.imgur.com/HRwJaUA.png"},  
{"url":"https://i.imgur.com/Njw5oJK.png"},  
{"url":"https://i.imgur.com/tstleaO.gif"},  
{"url":"https://i.imgur.com/YuqRyku.png"},  
{"url":"https://i.imgur.com/fXuiPMJ.png"},  
{"url":"https://i.imgur.com/KNr5AQC.gif"},  
{"url":"https://i.imgur.com/LGX8sqgh.jpg"},  
{"url":"https://i.imgur.com/63RUYFK.png"},  
{"url":"https://i.imgur.com/xvzOfCK.png"},  
{"url":"https://i.imgur.com/z3RSqSD.mp4"},  
{"url":"https://i.imgur.com/d0JVGtk.png"},  
{"url":"http://i.imgur.com/HyQIMxH.mp4"},  
{"url":"http://i.imgur.com/2mXE4vy.mp4"},  
{"url":"http://i.imgur.com/IBC7MrI.gif"},  
{"url":"http://i.imgur.com/Q4s5lSw.gif"},  
{"url":"http://i.imgur.com/0Da9VOE.jpg"},  
{"url":"http://i.imgur.com/cZ8NqH4.jpg"},  
{"url":"http://i.imgur.com/4VVYO5u.jpg"},  
{"url":"http://i.imgur.com/mAGfgb9.jpg"}, 
{"url":"http://i.imgur.com/4US2J4Q.gif"},  
{"url":"http://i.imgur.com/JwXmSRF.jpg"},  
{"url":"http://i.imgur.com/cjtvX.gif"},  
{"url":"https://i.imgur.com/MBdKmy4.png"},  
{"url":"https://i.imgur.com/WwBAiad.gif"},  
{"url":"https://i.imgur.com/AJH5bkL.png"},  
{"url":"https://i.imgur.com/vVXJaiq.mp4"},  
{"url":"https://i.imgur.com/140esbF.png"},  
{"url":"https://i.imgur.com/LtotzCl.mp4"},  
{"url":"https://i.imgur.com/mmMGcF9.png"},  
{"url":"https://i.imgur.com/BPfY4pB.gif"},  
{"url":"https://i.imgur.com/ix19s9Oh.jpg"},  
{"url":"https://i.imgur.com/iedm82u.png"},  
{"url":"https://i.imgur.com/mgDE6uQ.jpg"},  
{"url":"https://i.imgur.com/2Sbi7m6.gif"},  
{"url":"https://i.imgur.com/JtqySM3.png"},  
{"url":"http://i.imgur.com/vCNBDl3.jpg"},  
{"url":"http://i.imgur.com/H19KOSB.mp4"},  
{"url":"https://i.imgur.com/pp6RaQn.jpg"},  
{"url":"http://i.imgur.com/1p8waxR.jpg"},  
{"url":"http://i.imgur.com/htHMfgj.jpg"},  
{"url":"http://i.imgur.com/ATMzf7O.gif"},  
{"url":"http://i.imgur.com/tQOT8xJ.jpg"},  
{"url":"http://i.imgur.com/uyUrg35.jpg"},  
{"url":"http://i.imgur.com/uBr33HD.jpg"},  
{"url":"https://i.imgur.com/wIsxJCR.jpg"},  
{"url":"https://i.imgur.com/Y19DZVL.jpg"},  
{"url":"http://i.imgur.com/fw1ai4a.jpg"},  
{"url":"http://i.imgur.com/UAbEB0C.gif"},  
{"url":"http://i.imgur.com/zgPNDc0.gif"},  
{"url":"http://i.imgur.com/2fiJWGx.jpg"},  
{"url":"http://i.imgur.com/UHssN.gif"},  
{"url":"http://i.imgur.com/RatGX.gif"},  
{"url":"https://i.imgur.com/3qtOQaJ.gif"},  
{"url":"https://i.imgur.com/sF2LDUW.jpg"},  
{"url":"https://i.imgur.com/obt4uH5.gif"},  
{"url":"https://i.imgur.com/ag1OeCB.mp4"},  
{"url":"https://i.imgur.com/I4Fccvy.mp4"},  
{"url":"https://i.imgur.com/wWXioF2.png"},  
{"url":"http://i.imgur.com/0wL2EJ7.mp4"},  
{"url":"https://i.imgur.com/oB6R1De.jpg"},  
{"url":"http://i.imgur.com/gwI7E4y.jpg"},  
{"url":"http://i.imgur.com/SGedFPo.jpg"},  
{"url":"http://i.imgur.com/mu8NUjm.gif"},  
{"url":"http://i.imgur.com/AAdXxjt.gif"},  
{"url":"http://i.imgur.com/k0SDKgJ.jpg"},  
{"url":"http://i.imgur.com/9BRZOAs.gif"},  
{"url":"http://i.imgur.com/b5myKg9.gif"},  
{"url":"http://i.imgur.com/7eRSbue.mp4"},  
{"url":"http://i.imgur.com/du9ESbA.mp4"},  
{"url":"http://i.imgur.com/ZVhZYn7.jpg"},  
{"url":"http://i.imgur.com/dBzgZWs.mp4"},  
{"url":"http://i.imgur.com/sn9NoS0.jpg"},  
{"url":"http://i.imgur.com/6xgje.gif"},  
{"url":"http://i.imgur.com/8RcIY.gif"},  
{"url":"http://i.imgur.com/RMo1R.jpg"},  
{"url":"https://i.imgur.com/gCn4lx2.gif"},  
{"url":"https://i.imgur.com/shy5TVF.gif"},  
{"url":"https://i.imgur.com/S4JYPFi.png"},  
{"url":"https://i.imgur.com/xJpV9Ta.gif"},  
{"url":"https://i.imgur.com/QhCuPG6.png"},  
{"url":"https://i.imgur.com/E077IRC.gif"},  
{"url":"https://i.imgur.com/kITlEnx.png"},  
{"url":"http://i.imgur.com/tKEv6rN.jpg"},  
{"url":"http://i.imgur.com/1ghEm4k.gif"},  
{"url":"https://i.imgur.com/trJXnLg.gif"},  
{"url":"https://i.imgur.com/j3zT8WT.gif"},  
{"url":"https://i.imgur.com/0TMsqgc.jpg"},  
{"url":"https://i.imgur.com/QWPEST7.png"},  
{"url":"http://i.imgur.com/ROnR21s.jpg"},  
{"url":"http://i.imgur.com/HRwJaUA.jpg"},  
{"url":"http://i.imgur.com/z2d12H2.mp4"},  
{"url":"http://i.imgur.com/XMLc5vg.jpg"},  
{"url":"http://i.imgur.com/zdZBzod.jpg"},  
{"url":"https://i.imgur.com/MnMWfKk.jpg"},  
{"url":"http://i.imgur.com/D2dy5vH.gif"},  
{"url":"http://i.imgur.com/ptl78kp.jpg"},  
{"url":"http://i.imgur.com/gaIFDWf.jpg"},  
{"url":"http://i.imgur.com/b7iwd3B.gif"},  
{"url":"http://i.imgur.com/gr680Oc.gif"},  
{"url":"http://i.imgur.com/b6H45x1.gif"},  
{"url":"http://i.imgur.com/2Dl6RZY.gif"},  
{"url":"http://25.media.tumblr.com/tumblr_m8pix9Db0p1r7a0ufo1_1280.gif"},  
{"url":"https://i.imgur.com/9clD7Ay.gif"},  
{"url":"https://i.imgur.com/0wL2EJ7.gif"},  
{"url":"https://i.imgur.com/uOVLXAX.gif"},  
{"url":"https://i.imgur.com/MUn5oNj.png"},  
{"url":"http://i.imgur.com/WXl3i2i.jpg"},  
{"url":"https://i.imgur.com/aqauRHb.gif"},  
{"url":"https://i.imgur.com/uN1Kfhv.mp4"},  
{"url":"https://i.imgur.com/sjwx2Aw.jpg"},  
{"url":"http://i.imgur.com/Tejih7z.mp4"},  
{"url":"http://i.imgur.com/QsueRnp.mp4"},  
{"url":"http://i.imgur.com/6P9hJ87.gif"},  
{"url":"http://i.imgur.com/xVJSaLY.jpg"},  
{"url":"http://i.imgur.com/on2h5ub.jpg"},  
{"url":"https://i.imgur.com/h36Rtnah.jpg"},  
{"url":"http://i.imgur.com/Xbyv4dv.jpg"},  
{"url":"http://i.imgur.com/4UoPFSz.gif"},  
{"url":"http://i.imgur.com/Rig1zBF.gif"},  
{"url":"http://i.imgur.com/SzhZZWF.gif"},  
{"url":"http://i.imgur.com/3mCDmdg.gif"},  
{"url":"http://i.imgur.com/Nh2gFqm.gif"},  
{"url":"http://i.imgur.com/YONaO.jpg"},  
{"url":"http://i.imgur.com/sKTdg.jpg"},  
{"url":"http://i.imgur.com/D1POq.jpg"},  
{"url":"https://i.imgur.com/ha4nWW6.mp4"},  
{"url":"https://i.imgur.com/RSOxRt5.mp4"},  
{"url":"https://i.imgur.com/XBQGYaZ.png"},  
{"url":"https://i.imgur.com/wQdj4U1.mp4"},  
{"url":"https://i.imgur.com/SGedFPo.png"},  
{"url":"https://i.imgur.com/P9htvhc.png"},  
{"url":"https://i.imgur.com/W143T8T.mp4"},  
{"url":"https://i.imgur.com/3uBmGv0.mp4"},  
{"url":"https://i.imgur.com/lGLOaaw.png"},  
{"url":"https://i.imgur.com/1ITE4KG.png"},  
{"url":"http://i.imgur.com/SfRy09O.mp4"},  
{"url":"http://i.imgur.com/4ncIuQl.jpg"},  
{"url":"https://i.imgur.com/QeErcel.jpg"},  
{"url":"http://i.imgur.com/WIYC9Tb.mp4"},  
{"url":"http://i.imgur.com/xAAyq8Q.jpg"},  
{"url":"http://i.imgur.com/6mFzRZ3.gif"},  
{"url":"https://i.imgur.com/4HvYLnXh.jpg"},  
{"url":"http://i.imgur.com/Ne4dN19.jpg"},  
{"url":"http://i.imgur.com/w8UIFBL.gif"},  
{"url":"http://i.imgur.com/vux7Qpo.gif"},  
{"url":"http://i.imgur.com/T9r3YBM.gif"},  
{"url":"http://i.imgur.com/boy7IKK.gif"},  
{"url":"http://i.imgur.com/U9kPp9W.gif"},  
{"url":"http://i.imgur.com/fixPy1s.gif"},  
{"url":"http://i.imgur.com/1DZcZgQ.mp4"},  
{"url":"https://i.imgur.com/kEtIe5l.jpg"},  
{"url":"http://i.imgur.com/io9CG5L.jpg"},  
{"url":"http://i.imgur.com/8WCyrOC.gif"},  
{"url":"http://i.imgur.com/Kldia.jpg"},  
{"url":"http://i.imgur.com/fVPa5Xj.jpg"},  
{"url":"http://i.imgur.com/8nrS6.jpg"},  
{"url":"http://25.media.tumblr.com/tumblr_me2mfsWVD01rm2o2go1_500.gif"},  
{"url":"http://i.imgur.com/zDkse.jpg"},  
{"url":"http://24.media.tumblr.com/tumblr_md6nmvrglL1rgik52o1_500.gif"},  
{"url":"http://i.imgur.com/tQMAl.gif"},  
{"url":"https://i.imgur.com/hmuOStQ.mp4"},  
{"url":"http://i.imgur.com/v9eqkCk.jpg"},  
{"url":"https://i.imgur.com/YkqQixz.png"},  
{"url":"https://i.imgur.com/jBWezZ9.png"},  
{"url":"https://i.imgur.com/u795QdD.png"},  
{"url":"https://i.imgur.com/VUQ14sj.png"},  
{"url":"https://i.imgur.com/VScipqY.mp4"},  
{"url":"https://i.imgur.com/oaxSjML.gif"},  
{"url":"https://i.imgur.com/70bl7hp.gif"},  
{"url":"https://i.imgur.com/4Hm4YIU.gif"},  
{"url":"https://i.imgur.com/ig022QO.gif"},  
{"url":"https://i.imgur.com/6k7AOFH.gif"},  
{"url":"http://i.imgur.com/cRNGIPl.jpg"},  
{"url":"http://i.imgur.com/LtotzCl.gif"},  
{"url":"http://i.imgur.com/rLWYyhX.gif"},  
{"url":"http://i.imgur.com/JRRSZM9.gif"},  
{"url":"http://i.imgur.com/AjetaVm.gif"},  
{"url":"http://i.imgur.com/UDpvXgb.gif"},  
{"url":"http://i.imgur.com/CKNqCG2.jpg"},  
{"url":"http://i.imgur.com/xTeKXfB.gif"},  
{"url":"https://i.imgur.com/GrmHGDd.jpg"},  
{"url":"http://i.imgur.com/JziWSnp.gif"},  
{"url":"http://i.imgur.com/NpbKQ5L.jpg"},  
{"url":"http://i.imgur.com/H6ZW0r9.jpg"},  
{"url":"http://i.imgur.com/ZLRFifJ.jpg"},  
{"url":"http://i.imgur.com/8TZ0z.jpg"},  
{"url":"http://25.media.tumblr.com/tumblr_mcgs12oPql1r8k6sgo1_500.gif"},  
{"url":"http://i.imgur.com/z1p4J.gif"},  
{"url":"http://i.imgur.com/TcNBp.jpg"}
]
